cogwit_sdk/__init__.py
cogwit_sdk/responses.py
cogwit_sdk/cogwit/cogwit.py
cogwit_sdk/infrastructure/json_encoder.py
cogwit_sdk/infrastructure/send_api_request.py
cogwit_sdk/modules/search/SearchType.py
cogwit_sdk-0.1.7.dist-info/METADATA
cogwit_sdk-0.1.7.dist-info/WHEEL
cogwit_sdk-0.1.7.dist-info/licenses/LICENSE
cogwit_sdk-0.1.7.dist-info/RECORD
