Metadata-Version: 2.4
Name: cogwit_sdk
Version: 0.1.7
Summary: SDK for communicating with the Cogwit API
License-File: LICENSE
Requires-Python: <=3.13,>=3.10
Requires-Dist: aiohttp==3.12.15
Requires-Dist: pydantic==2.11.7
